elbowplot/__init__.py
elbowplot/core.py
tests/__init__.py
tests/test_core.py
elbowplot-0.3.0.dist-info/LICENSE
elbowplot-0.3.0.dist-info/METADATA
elbowplot-0.3.0.dist-info/WHEEL
elbowplot-0.3.0.dist-info/top_level.txt
elbowplot-0.3.0.dist-info/RECORD
