Metadata-Version: 2.1
Name: elbowplot
Version: 0.3.0
Summary: A simple library to plot the elbow plot for K-means clustering.
Home-page: https://github.com/yourusername/elbowplot
Author: Your Name
Author-email: your.email@example.com
Classifier: Development Status :: 3 - Alpha
Classifier: Intended Audience :: Developers
Classifier: License :: OSI Approved :: MIT License
Classifier: Programming Language :: Python :: 3
Classifier: Programming Language :: Python :: 3.7
License-File: LICENSE
